setup.cfg
setup.py
data/loc_code.txt
real_estate_in_korea/__init__.py
real_estate_in_korea/__main__.py
real_estate_in_korea/data.py
real_estate_in_korea/defaults.py
real_estate_in_korea/local_code.py
real_estate_in_korea/main.py
real_estate_in_korea/options.py
real_estate_in_korea/version.py
real_estate_in_korea.egg-info/PKG-INFO
real_estate_in_korea.egg-info/SOURCES.txt
real_estate_in_korea.egg-info/dependency_links.txt
real_estate_in_korea.egg-info/requires.txt
real_estate_in_korea.egg-info/top_level.txt
scripts/real_estate_in_korea