Metadata-Version: 1.1
Name: real-estate-in-korea
Version: 0.2.0
Summary: Real estate in korea apt check for Python
Home-page: https://github.com/byung-u/real_estate_in_korea
Author: Byungwoo Jeon
Author-email: iam.byungwoo@gmail.com
License: MIT License
Download-URL: https://github.com/byung-u/real_estate_in_korea/archive/0.2.0.tar.gz
Keywords: realestate,korea
Platform: UNKNOWN
Classifier: Development Status :: 5 - Production/Stable
Classifier: Environment :: Console
Classifier: Intended Audience :: Developers
Classifier: Topic :: Software Development
Classifier: License :: OSI Approved :: MIT License
Classifier: Operating System :: POSIX
Classifier: Programming Language :: Python :: 3
Classifier: Programming Language :: Python :: 3.3
Classifier: Programming Language :: Python :: 3.4
Classifier: Programming Language :: Python :: 3.5
Classifier: Programming Language :: Python :: 3.6
